{"name":"lib_1263a1baa63637b4aaf5","content":{"./node_modules/redux-thunk/es/index.js":{"id":3894,"buildMeta":{"exportsType":"namespace"},"exports":["default"]},"./node_modules/react-dom/index.js":{"id":3935,"buildMeta":{"exportsType":"dynamic","defaultObject":"redirect"},"exports":["__SECRET_INTERNALS_DO_NOT_USE_OR_YOU_WILL_BE_FIRED","createPortal","findDOMNode","flushSync","hydrate","render","unmountComponentAtNode","unstable_batchedUpdates","unstable_createPortal","unstable_renderSubtreeIntoContainer","version"]},"./node_modules/prop-types/index.js":{"id":5697,"buildMeta":{}},"./node_modules/redux/es/redux.js":{"id":5857,"buildMeta":{"exportsType":"namespace"},"exports":["__DO_NOT_USE__ActionTypes","applyMiddleware","bindActionCreators","combineReducers","compose","createStore"]},"./node_modules/react-app-polyfill/ie9.js":{"id":6961,"buildMeta":{}},"./node_modules/react/index.js":{"id":7294,"buildMeta":{"exportsType":"dynamic","defaultObject":"redirect"},"exports":["Children","Component","Fragment","Profiler","PureComponent","StrictMode","Suspense","__SECRET_INTERNALS_DO_NOT_USE_OR_YOU_WILL_BE_FIRED","cloneElement","createContext","createElement","createFactory","createRef","forwardRef","isValidElement","lazy","memo","useCallback","useContext","useDebugValue","useEffect","useImperativeHandle","useLayoutEffect","useMemo","useReducer","useRef","useState","version"]}}}